odoo9_addon_website_form_recaptcha-9.0.1.0.0.99.dev24-py3.8-nspkg.pth
odoo_addons/website_form_recaptcha/README.rst
odoo_addons/website_form_recaptcha/__init__.py
odoo_addons/website_form_recaptcha/__openerp__.py
odoo_addons/website_form_recaptcha/controllers/__init__.py
odoo_addons/website_form_recaptcha/controllers/main.py
odoo_addons/website_form_recaptcha/data/ir_config_parameter_data.xml
odoo_addons/website_form_recaptcha/i18n/af.po
odoo_addons/website_form_recaptcha/i18n/am.po
odoo_addons/website_form_recaptcha/i18n/ar.po
odoo_addons/website_form_recaptcha/i18n/bg.po
odoo_addons/website_form_recaptcha/i18n/bs.po
odoo_addons/website_form_recaptcha/i18n/ca.po
odoo_addons/website_form_recaptcha/i18n/cs.po
odoo_addons/website_form_recaptcha/i18n/da.po
odoo_addons/website_form_recaptcha/i18n/de.po
odoo_addons/website_form_recaptcha/i18n/el.po
odoo_addons/website_form_recaptcha/i18n/el_GR.po
odoo_addons/website_form_recaptcha/i18n/en_GB.po
odoo_addons/website_form_recaptcha/i18n/es.po
odoo_addons/website_form_recaptcha/i18n/es_AR.po
odoo_addons/website_form_recaptcha/i18n/es_CL.po
odoo_addons/website_form_recaptcha/i18n/es_CO.po
odoo_addons/website_form_recaptcha/i18n/es_CR.po
odoo_addons/website_form_recaptcha/i18n/es_DO.po
odoo_addons/website_form_recaptcha/i18n/es_EC.po
odoo_addons/website_form_recaptcha/i18n/es_ES.po
odoo_addons/website_form_recaptcha/i18n/es_MX.po
odoo_addons/website_form_recaptcha/i18n/es_PE.po
odoo_addons/website_form_recaptcha/i18n/es_PY.po
odoo_addons/website_form_recaptcha/i18n/es_VE.po
odoo_addons/website_form_recaptcha/i18n/et.po
odoo_addons/website_form_recaptcha/i18n/eu.po
odoo_addons/website_form_recaptcha/i18n/fa.po
odoo_addons/website_form_recaptcha/i18n/fi.po
odoo_addons/website_form_recaptcha/i18n/fr.po
odoo_addons/website_form_recaptcha/i18n/fr_CA.po
odoo_addons/website_form_recaptcha/i18n/fr_CH.po
odoo_addons/website_form_recaptcha/i18n/gl.po
odoo_addons/website_form_recaptcha/i18n/gl_ES.po
odoo9_addon_website_form_recaptcha-9.0.1.0.0.99.dev24.dist-info/METADATA
odoo9_addon_website_form_recaptcha-9.0.1.0.0.99.dev24.dist-info/WHEEL
odoo9_addon_website_form_recaptcha-9.0.1.0.0.99.dev24.dist-info/namespace_packages.txt
odoo9_addon_website_form_recaptcha-9.0.1.0.0.99.dev24.dist-info/top_level.txt
odoo9_addon_website_form_recaptcha-9.0.1.0.0.99.dev24.dist-info/RECORD
