Metadata-Version: 2.1
Name: odoo9-addon-website-form-recaptcha
Version: 9.0.1.0.0.99.dev24
Summary: Provides a ReCaptcha field for Website Forms
Home-page: https://laslabs.com/
Author: LasLabs, Odoo Community Association
License: AGPL-3
Platform: UNKNOWN
Classifier: Programming Language :: Python
Classifier: Framework :: Odoo
Classifier: Framework :: Odoo :: 9.0
Classifier: License :: OSI Approved :: GNU Affero General Public License v3
Requires-Python: ~=2.7
Requires-Dist: odoo (<9.1a,>=9.0a)
